syosetumaster/__init__.py
syosetumaster/syosetumaster.py
syosetumaster/book/__init__.py
syosetumaster/book/book.py
syosetumaster/crawl/__init__.py
syosetumaster/crawl/crawl.py
syosetumaster/local/__init__.py
syosetumaster/local/baselocal.py
syosetumaster/local/util.py
syosetumaster/syosetu/__init__.py
syosetumaster/syosetu/syosetu.py
syosetumaster/translate_gpt_IO/__init__.py
syosetumaster/translate_gpt_IO/translate_gpt_IO.py
syosetumaster/translate_gpt_IO/gpt_IO/__init__.py
syosetumaster/translate_gpt_IO/gpt_IO/gpt_IO.py
syosetumaster-0.1.1.dist-info/METADATA
syosetumaster-0.1.1.dist-info/WHEEL
syosetumaster-0.1.1.dist-info/top_level.txt
syosetumaster-0.1.1.dist-info/RECORD
