Metadata-Version: 2.1
Name: syosetumaster
Version: 0.1.1
Summary: simple crawling + translating project with syosetuka ni narou
Home-page: https://github.com/Hijkstuv/syosetumaster
Author: Hijkstuv
Author-email: kingcrush1729@gmail.com
Classifier: Programming Language :: Python :: 3
Classifier: License :: OSI Approved :: MIT License
Classifier: Operating System :: OS Independent
Requires-Python: >=3.10
Requires-Dist: selenium==4.24.0
Requires-Dist: openai==1.95.1
Requires-Dist: pydantic==2.10.6
Requires-Dist: python-dotenv==0.21.0
Requires-Dist: typing-extensions==4.12.2
